dj_boilerplate_generator/__init__.py
dj_boilerplate_generator/__main__.py
dj_boilerplate_generator/cli copy.py
dj_boilerplate_generator/cli.py
dj_boilerplate_generator/main.py
dj_boilerplate_generator/generators/__init__.py
dj_boilerplate_generator/generators/base_generator.py
dj_boilerplate_generator/generators/django_core.py
dj_boilerplate_generator/generators/enhanced_generator.py
dj_boilerplate_generator/generators/project_structure.py
dj_boilerplate_generator/generators/template_engine.py
dj_boilerplate_generator/templates/__init__.py
dj_boilerplate_generator/templates/phase1/__init__.py
dj_boilerplate_generator/templates/phase1/core_app/__init__.py
dj_boilerplate_generator/templates/phase1/project_root/__init__.py
dj_boilerplate_generator/templates/phase1/settings/__init__.py
dj_boilerplate_generator/templates/phase1/settings/base.py.j2
dj_boilerplate_generator/templates/phase1/settings/development.py.j2
dj_boilerplate_generator/templates/phase1/settings/production.py.j2
dj_boilerplate_generator/templates/phase1/settings/testing.py.j2
dj_boilerplate_generator/use/__init__.py
dj_boilerplate_generator/utils/__init__.py
dj_boilerplate_generator/utils/file_ops.py
dj_boilerplate_generator/utils/security.py
dj_boilerplate_generator/utils/validators.py
dj_boilerplate_generator-3.0.dist-info/licenses/LICENSE
dj_boilerplate_generator-3.0.dist-info/METADATA
dj_boilerplate_generator-3.0.dist-info/WHEEL
dj_boilerplate_generator-3.0.dist-info/entry_points.txt
dj_boilerplate_generator-3.0.dist-info/top_level.txt
dj_boilerplate_generator-3.0.dist-info/RECORD
