Metadata-Version: 2.4
Name: dj-boilerplate-generator
Version: 3.0
Summary: Ultimate Django Boilerplate Generator - Enterprise Edition
Author-email: HttpError451 <contactshaikhwasim@gmail.com>
License: MIT
Project-URL: Homepage, https://github.com/contactshaikhwasim/dj-boilerplate-generator
Keywords: django,boilerplate,generator,enterprise
Classifier: Development Status :: 4 - Beta
Classifier: Intended Audience :: Developers
Classifier: License :: OSI Approved :: MIT License
Classifier: Operating System :: OS Independent
Classifier: Programming Language :: Python :: 3
Classifier: Programming Language :: Python :: 3.10
Classifier: Programming Language :: Python :: 3.11
Classifier: Programming Language :: Python :: 3.12
Requires-Python: >=3.10
License-File: LICENSE
Requires-Dist: click>=8.0.0
Requires-Dist: questionary>=1.10.0
Requires-Dist: rich>=13.0.0
Requires-Dist: jinja2>=3.0.0
Requires-Dist: python-decouple>=3.8
Requires-Dist: dj-database-url>=1.0.0
Dynamic: license-file
